micropython_branch_manager/__init__.py
micropython_branch_manager/__main__.py
micropython_branch_manager/_version.py
micropython_branch_manager/branch_sync.py
micropython_branch_manager/cli.py
micropython_branch_manager/config.py
micropython_branch_manager/exceptions.py
micropython_branch_manager/git.py
micropython_branch_manager/github.py
micropython_branch_manager/pr.py
micropython_branch_manager/rebase.py
micropython_branch_manager/update_branch.py
micropython_branch_manager-1.0.0.dist-info/METADATA
micropython_branch_manager-1.0.0.dist-info/WHEEL
micropython_branch_manager-1.0.0.dist-info/entry_points.txt
micropython_branch_manager-1.0.0.dist-info/licenses/LICENSE
micropython_branch_manager-1.0.0.dist-info/RECORD
