Metadata-Version: 2.4
Name: micropython-branch-manager
Version: 1.0.0
Summary: Tool for managing MicroPython fork integration branches
License-Expression: MIT
License-File: LICENSE
Requires-Python: >=3.11
Requires-Dist: cyclopts>=3.0
Requires-Dist: pydantic>=2.0
